[
  {
    "world_id": "WORLD-OCEAN_RESEARCH_OBSERVATORY",
    "topic": "Why Octopuses Have Three Hearts",
    "production_id": "octopus_test",
    "channel": "",
    "at": "2026-07-14T03:31:27.110675+00:00"
  },
  {
    "world_id": "WORLD-AI_LABORATORY",
    "topic": "How Artificial Intelligence Learns Patterns",
    "production_id": "ai_patterns",
    "channel": "",
    "at": "2026-07-14T03:31:27.223447+00:00"
  },
  {
    "world_id": "WORLD-AI_LABORATORY",
    "topic": "How Artificial Intelligence Learns Patterns",
    "production_id": "sep_test",
    "channel": "",
    "at": "2026-07-14T03:31:27.302164+00:00"
  },
  {
    "world_id": "WORLD-OCEAN_RESEARCH_OBSERVATORY",
    "topic": "Octopus hearts",
    "production_id": "req_test",
    "channel": "",
    "at": "2026-07-14T03:31:27.398792+00:00"
  },
  {
    "world_id": "WORLD-DNA_INTERIOR",
    "topic": "DNA helix",
    "production_id": "dna_t",
    "channel": "",
    "at": "2026-07-14T03:31:27.438255+00:00"
  },
  {
    "world_id": "WORLD-OCEAN_RESEARCH_OBSERVATORY",
    "topic": "Why Octopuses Have Three Hearts",
    "production_id": "octopus_three_hearts",
    "channel": "",
    "at": "2026-07-14T03:31:38.335250+00:00"
  },
  {
    "world_id": "WORLD-AI_LABORATORY",
    "topic": "How Artificial Intelligence Learns Patterns",
    "production_id": "ai_learns_patterns",
    "channel": "",
    "at": "2026-07-14T03:31:38.986928+00:00"
  },
  {
    "world_id": "WORLD-OCEAN_RESEARCH_OBSERVATORY",
    "topic": "Why Octopuses Have Three Hearts",
    "production_id": "octopus_test",
    "channel": "",
    "at": "2026-07-14T03:31:39.696267+00:00"
  },
  {
    "world_id": "WORLD-AI_LABORATORY",
    "topic": "How Artificial Intelligence Learns Patterns",
    "production_id": "ai_patterns",
    "channel": "",
    "at": "2026-07-14T03:31:39.809208+00:00"
  },
  {
    "world_id": "WORLD-AI_LABORATORY",
    "topic": "How Artificial Intelligence Learns Patterns",
    "production_id": "sep_test",
    "channel": "",
    "at": "2026-07-14T03:31:39.887796+00:00"
  },
  {
    "world_id": "WORLD-OCEAN_RESEARCH_OBSERVATORY",
    "topic": "Octopus hearts",
    "production_id": "req_test",
    "channel": "",
    "at": "2026-07-14T03:31:40.003229+00:00"
  },
  {
    "world_id": "WORLD-DNA_INTERIOR",
    "topic": "DNA helix",
    "production_id": "dna_t",
    "channel": "",
    "at": "2026-07-14T03:31:40.043034+00:00"
  },
  {
    "world_id": "WORLD-OCEAN_RESEARCH_OBSERVATORY",
    "topic": "Why Octopuses Have Three Hearts",
    "production_id": "octopus_three_hearts_20260714T033454",
    "channel": "",
    "at": "2026-07-14T03:34:54.505556+00:00"
  },
  {
    "world_id": "WORLD-OCEAN_RESEARCH_OBSERVATORY",
    "topic": "The hidden truth: Why Octopuses Have Three Hearts In A Ed...",
    "production_id": "octopus_three_hearts_20260714T033454",
    "channel": "",
    "at": "2026-07-14T03:36:55.232324+00:00"
  },
  {
    "world_id": "WORLD-OCEAN_RESEARCH_OBSERVATORY",
    "topic": "Why Octopuses Have Three Hearts",
    "production_id": "octopus_test",
    "channel": "",
    "at": "2026-07-14T03:44:18.328044+00:00"
  },
  {
    "world_id": "WORLD-AI_LABORATORY",
    "topic": "How Artificial Intelligence Learns Patterns",
    "production_id": "ai_patterns",
    "channel": "",
    "at": "2026-07-14T03:44:18.448669+00:00"
  },
  {
    "world_id": "WORLD-AI_LABORATORY",
    "topic": "How Artificial Intelligence Learns Patterns",
    "production_id": "sep_test",
    "channel": "",
    "at": "2026-07-14T03:44:18.532678+00:00"
  },
  {
    "world_id": "WORLD-OCEAN_RESEARCH_OBSERVATORY",
    "topic": "Octopus hearts",
    "production_id": "req_test",
    "channel": "",
    "at": "2026-07-14T03:44:18.634644+00:00"
  },
  {
    "world_id": "WORLD-DNA_INTERIOR",
    "topic": "DNA helix",
    "production_id": "dna_t",
    "channel": "",
    "at": "2026-07-14T03:44:18.695194+00:00"
  },
  {
    "world_id": "WORLD_SUBURBAN_NEIGHBORHOOD",
    "topic": "Why Fire Hydrants Are Different Colors",
    "production_id": "ops_611eb1052d",
    "channel": "",
    "at": "2026-07-14T13:25:41.670508+00:00"
  },
  {
    "world_id": "WORLD_SUBURBAN_NEIGHBORHOOD",
    "topic": "Why Fire Hydrants Are Different Colors",
    "production_id": "ops_1ea9ba5073",
    "channel": "",
    "at": "2026-07-14T13:29:13.267812+00:00"
  },
  {
    "world_id": "WORLD-OCEAN_RESEARCH_OBSERVATORY",
    "topic": "Are Leprechauns Real? The Truth Behind Ireland's Tiny Tricksters",
    "production_id": "ops_826e121fa1",
    "channel": "",
    "at": "2026-07-14T13:41:08.786555+00:00"
  },
  {
    "world_id": "WORLD-OCEAN_RESEARCH_OBSERVATORY",
    "topic": "Are Leprechauns Real? The Truth Behind Ireland's Tiny Tricksters",
    "production_id": "ops_97831cea0f",
    "channel": "",
    "at": "2026-07-14T13:42:31.251538+00:00"
  },
  {
    "world_id": "WORLD-OCEAN_RESEARCH_OBSERVATORY",
    "topic": "Are Leprechauns Real? The Truth Behind Ireland's Tiny Tricksters",
    "production_id": "ops_32ce3aa7fd",
    "channel": "",
    "at": "2026-07-14T13:43:52.939657+00:00"
  },
  {
    "world_id": "WORLD-OCEAN_RESEARCH_OBSERVATORY",
    "topic": "The Parasite You May Never Know You Have",
    "production_id": "ops_d571a6407f",
    "channel": "",
    "at": "2026-07-15T23:03:14.034957+00:00"
  },
  {
    "world_id": "WORLD-OCEAN_RESEARCH_OBSERVATORY",
    "topic": "The Parasite You May Never Know You Have",
    "production_id": "ops_82b47c10aa",
    "channel": "",
    "at": "2026-07-15T23:07:35.481645+00:00"
  },
  {
    "world_id": "WORLD-OCEAN_RESEARCH_OBSERVATORY",
    "topic": "The Parasite You May Never Know You Have",
    "production_id": "ops_f9daa1da06",
    "channel": "",
    "at": "2026-07-15T23:08:50.929432+00:00"
  }
]
