{
  "title": "Black Smokers Explained",
  "target_duration_seconds": 60,
  "tone": "mysterious",
  "primary_emotion": "curiosity",
  "script_summary": "Exploring the fascinating world of black smokers and their underwater ecosystems.",
  "segments": [
    {
      "segment_number": 1,
      "start_time": 0.0,
      "end_time": 2.0,
      "segment_type": "hook",
      "voiceover": "Superheated mineral-rich water erupts from seafloor vents, building chimneys in the dark.",
      "emotion": "curiosity",
      "delivery": "quiet and suspenseful",
      "retention_device": "open loop"
    },
    {
      "segment_number": 2,
      "start_time": 2.0,
      "end_time": 10.0,
      "segment_type": "context",
      "voiceover": "These black smokers are found deep in the ocean, where sunlight never reaches.",
      "emotion": "curiosity",
      "delivery": "informative",
      "retention_device": "curiosity gap"
    },
    {
      "segment_number": 3,
      "start_time": 10.0,
      "end_time": 18.0,
      "segment_type": "escalation",
      "voiceover": "They spew out metal-rich fluids at temperatures over 400 degrees Celsius!",
      "emotion": "curiosity",
      "delivery": "excited",
      "retention_device": "surprising fact"
    },
    {
      "segment_number": 4,
      "start_time": 18.0,
      "end_time": 26.0,
      "segment_type": "evidence",
      "voiceover": "These conditions create unique habitats, home to extremophiles and bizarre creatures.",
      "emotion": "curiosity",
      "delivery": "engaging",
      "retention_device": "visual imagery"
    },
    {
      "segment_number": 5,
      "start_time": 26.0,
      "end_time": 34.0,
      "segment_type": "payoff",
      "voiceover": "Black smokers challenge our understanding of life, thriving where nothing else can.",
      "emotion": "curiosity",
      "delivery": "thought-provoking",
      "retention_device": "conclusive thought"
    },
    {
      "segment_number": 6,
      "start_time": 34.0,
      "end_time": 60.0,
      "segment_type": "cta",
      "voiceover": "Want to dive deeper? Like and subscribe for more ocean mysteries!",
      "emotion": "curiosity",
      "delivery": "inviting",
      "retention_device": "call to action"
    }
  ],
  "full_voiceover": "Superheated mineral-rich water erupts from seafloor vents, building chimneys in the dark. These black smokers are found deep in the ocean, where sunlight never reaches. They spew out metal-rich fluids at temperatures over 400 degrees Celsius! These conditions create unique habitats, home to extremophiles and bizarre creatures. Black smokers challenge our understanding of life, thriving where nothing else can. Want to dive deeper? Like and subscribe for more ocean mysteries!",
  "call_to_action": "Like and subscribe for more ocean mysteries!",
  "estimated_word_count": 130,
  "generated_at": "2026-07-10T17:02:05.956405+00:00",
  "source": "ai"
}