{
  "render_package_version": "2.0",
  "render_engine_version": "1.0.0",
  "title": "River deltas",
  "created_at": "2026-07-10T17:42:44.329259+00:00",
  "output_format": {
    "aspect_ratio": "9:16",
    "resolution": {
      "width": 1080,
      "height": 1920
    },
    "container": "mp4",
    "video_codec": "h264",
    "audio_codec": "aac",
    "fps": 30,
    "orientation": "vertical",
    "platforms": [
      "youtube_shorts",
      "tiktok",
      "instagram_reels",
      "facebook_reels"
    ]
  },
  "platforms": [
    "youtube_shorts",
    "tiktok",
    "instagram_reels",
    "facebook_reels"
  ],
  "resolution": "1080x1920",
  "aspect_ratio": "9:16",
  "duration_sec": 60.0,
  "timeline": {
    "fps": 30,
    "total_duration_sec": 60.0,
    "segment_count": 7,
    "segments": [
      {
        "scene_id": 1,
        "start_time": 0.0,
        "end_time": 2.0,
        "duration": 2.0,
        "narration_reference": "narration/scene_1",
        "visual_reference": "visual/scene_1",
        "caption_reference": "captions/scene_1",
        "audio_reference": "audio/scene_1",
        "transition_in": "cut",
        "transition_out": "cut",
        "motion_effect": "quick_punch_in",
        "overlay_text": "Science has a clearer",
        "render_status": "planned"
      },
      {
        "scene_id": 2,
        "start_time": 2.0,
        "end_time": 10.0,
        "duration": 8.0,
        "narration_reference": "narration/scene_2",
        "visual_reference": "visual/scene_2",
        "caption_reference": "captions/scene_2",
        "audio_reference": "audio/scene_2",
        "transition_in": "cut",
        "transition_out": "cut",
        "motion_effect": "static",
        "overlay_text": "River deltas form where",
        "render_status": "planned"
      },
      {
        "scene_id": 3,
        "start_time": 10.0,
        "end_time": 18.0,
        "duration": 8.0,
        "narration_reference": "narration/scene_3",
        "visual_reference": "visual/scene_3",
        "caption_reference": "captions/scene_3",
        "audio_reference": "audio/scene_3",
        "transition_in": "cut",
        "transition_out": "cut",
        "motion_effect": "static",
        "overlay_text": "But did you know",
        "render_status": "planned"
      },
      {
        "scene_id": 4,
        "start_time": 18.0,
        "end_time": 26.0,
        "duration": 8.0,
        "narration_reference": "narration/scene_4",
        "visual_reference": "visual/scene_4",
        "caption_reference": "captions/scene_4",
        "audio_reference": "audio/scene_4",
        "transition_in": "cut",
        "transition_out": "cut",
        "motion_effect": "static",
        "overlay_text": "Deltas provide fertile land",
        "render_status": "planned"
      },
      {
        "scene_id": 5,
        "start_time": 26.0,
        "end_time": 34.0,
        "duration": 8.0,
        "narration_reference": "narration/scene_5",
        "visual_reference": "visual/scene_5",
        "caption_reference": "captions/scene_5",
        "audio_reference": "audio/scene_5",
        "transition_in": "cut",
        "transition_out": "cut",
        "motion_effect": "static",
        "overlay_text": "Yet, climate change threatens",
        "render_status": "planned"
      },
      {
        "scene_id": 6,
        "start_time": 34.0,
        "end_time": 50.0,
        "duration": 16.0,
        "narration_reference": "narration/scene_6",
        "visual_reference": "visual/scene_6",
        "caption_reference": "captions/scene_6",
        "audio_reference": "audio/scene_6",
        "transition_in": "cut",
        "transition_out": "cut",
        "motion_effect": "static",
        "overlay_text": "By protecting deltas, we",
        "render_status": "planned"
      },
      {
        "scene_id": 7,
        "start_time": 50.0,
        "end_time": 60.0,
        "duration": 10.0,
        "narration_reference": "narration/scene_7",
        "visual_reference": "visual/scene_7",
        "caption_reference": "captions/scene_7",
        "audio_reference": "audio/scene_7",
        "transition_in": "cut",
        "transition_out": "cut",
        "motion_effect": "static",
        "overlay_text": "Follow for more fascinating",
        "render_status": "planned"
      }
    ],
    "transitions": [
      {
        "from_scene": 1,
        "to_scene": 2,
        "type": "cut",
        "duration_sec": 0.0,
        "sound_cue": "",
        "source_language": "hard cut"
      },
      {
        "from_scene": 2,
        "to_scene": 3,
        "type": "cut",
        "duration_sec": 0.0,
        "sound_cue": "",
        "source_language": "hard cut"
      },
      {
        "from_scene": 3,
        "to_scene": 4,
        "type": "cut",
        "duration_sec": 0.0,
        "sound_cue": "",
        "source_language": "hard cut"
      },
      {
        "from_scene": 4,
        "to_scene": 5,
        "type": "cut",
        "duration_sec": 0.0,
        "sound_cue": "",
        "source_language": "hard cut"
      },
      {
        "from_scene": 5,
        "to_scene": 6,
        "type": "cut",
        "duration_sec": 0.0,
        "sound_cue": "",
        "source_language": "hard cut"
      },
      {
        "from_scene": 6,
        "to_scene": 7,
        "type": "cut",
        "duration_sec": 0.0,
        "sound_cue": "",
        "source_language": "hard cut"
      }
    ],
    "warnings": []
  },
  "scene_render_plan": [
    {
      "scene_id": 1,
      "visual_asset_type": "ai_image",
      "image_prompt": "Hook visual: Science has a clearer story about river deltas than social media does.",
      "video_prompt": "Cinematic motion: Hook visual: Science has a clearer story about river deltas than social media does.",
      "stock_footage_query": "",
      "user_footage_slot": {
        "reserved": false,
        "status": "empty",
        "notes": ""
      },
      "avatar_footage_slot": {
        "reserved": false,
        "status": "empty",
        "notes": ""
      },
      "reaction_footage_slot": {
        "reserved": false,
        "status": "empty",
        "notes": ""
      },
      "camera_movement": {
        "motion": "subtle push",
        "angle": "",
        "shot_type": "medium"
      },
      "effect": {
        "name": "quick_punch_in",
        "zoom": {
          "start_scale": 1.0,
          "end_scale": 1.188
        },
        "pan": {
          "direction": "none",
          "amount_pct": 0.0
        },
        "ken_burns": false,
        "intensity": 70
      },
      "text_overlays": [
        {
          "text": "Science has a clearer",
          "treatment": "",
          "start_sec": 0.0,
          "end_sec": 2.0
        }
      ],
      "caption_placement": "bottom third, safe zone",
      "sound_cues": [
        {
          "cue": "bass hit",
          "at_sec": 0.0,
          "track": "sfx"
        }
      ],
      "narration": "Science has a clearer story about river deltas than social media does.",
      "duration_sec": 2.0,
      "resolved_asset": {
        "path": "runtime://image/demo",
        "uri": "",
        "image_url": "",
        "b64_json": "",
        "provider": "demo",
        "placeholder": true,
        "status": "mock",
        "prompt": "Hook visual: Science has a clearer story about river deltas than social media does.",
        "width": 1080,
        "height": 1920,
        "error": "",
        "scene_number": 1
      }
    },
    {
      "scene_id": 2,
      "visual_asset_type": "ai_image",
      "image_prompt": "Context visual: River deltas form where rivers meet the sea, creating unique ecosystems.",
      "video_prompt": "Cinematic motion: Context visual: River deltas form where rivers meet the sea, creating unique ecosystems.",
      "stock_footage_query": "",
      "user_footage_slot": {
        "reserved": false,
        "status": "empty",
        "notes": ""
      },
      "avatar_footage_slot": {
        "reserved": false,
        "status": "empty",
        "notes": ""
      },
      "reaction_footage_slot": {
        "reserved": false,
        "status": "empty",
        "notes": ""
      },
      "camera_movement": {
        "motion": "static",
        "angle": "",
        "shot_type": "medium"
      },
      "effect": {
        "name": "static",
        "zoom": {
          "start_scale": 1.0,
          "end_scale": 1.0
        },
        "pan": {
          "direction": "none",
          "amount_pct": 0.0
        },
        "ken_burns": false,
        "intensity": 45
      },
      "text_overlays": [
        {
          "text": "River deltas form where",
          "treatment": "",
          "start_sec": 2.0,
          "end_sec": 10.0
        }
      ],
      "caption_placement": "bottom third, safe zone",
      "sound_cues": [
        {
          "cue": "whoosh",
          "at_sec": 2.0,
          "track": "sfx"
        }
      ],
      "narration": "River deltas form where rivers meet the sea, creating unique ecosystems.",
      "duration_sec": 8.0,
      "resolved_asset": {
        "path": "runtime://image/demo",
        "uri": "",
        "image_url": "",
        "b64_json": "",
        "provider": "demo",
        "placeholder": true,
        "status": "mock",
        "prompt": "Context visual: River deltas form where rivers meet the sea, creating unique ecosystems.",
        "width": 1080,
        "height": 1920,
        "error": "",
        "scene_number": 2
      }
    },
    {
      "scene_id": 3,
      "visual_asset_type": "ai_image",
      "image_prompt": "Escalation visual: But did you know they're also vital for human life?",
      "video_prompt": "Cinematic motion: Escalation visual: But did you know they're also vital for human life?",
      "stock_footage_query": "",
      "user_footage_slot": {
        "reserved": false,
        "status": "empty",
        "notes": ""
      },
      "avatar_footage_slot": {
        "reserved": false,
        "status": "empty",
        "notes": ""
      },
      "reaction_footage_slot": {
        "reserved": false,
        "status": "empty",
        "notes": ""
      },
      "camera_movement": {
        "motion": "static",
        "angle": "",
        "shot_type": "medium"
      },
      "effect": {
        "name": "static",
        "zoom": {
          "start_scale": 1.0,
          "end_scale": 1.0
        },
        "pan": {
          "direction": "none",
          "amount_pct": 0.0
        },
        "ken_burns": false,
        "intensity": 45
      },
      "text_overlays": [
        {
          "text": "But did you know",
          "treatment": "",
          "start_sec": 10.0,
          "end_sec": 18.0
        }
      ],
      "caption_placement": "bottom third, safe zone",
      "sound_cues": [
        {
          "cue": "whoosh",
          "at_sec": 10.0,
          "track": "sfx"
        }
      ],
      "narration": "But did you know they're also vital for human life?",
      "duration_sec": 8.0,
      "resolved_asset": {
        "path": "runtime://image/demo",
        "uri": "",
        "image_url": "",
        "b64_json": "",
        "provider": "demo",
        "placeholder": true,
        "status": "mock",
        "prompt": "Escalation visual: But did you know they're also vital for human life?",
        "width": 1080,
        "height": 1920,
        "error": "",
        "scene_number": 3
      }
    },
    {
      "scene_id": 4,
      "visual_asset_type": "ai_image",
      "image_prompt": "Evidence visual: Deltas provide fertile land for agriculture and act as natural buffers against storms.",
      "video_prompt": "Cinematic motion: Evidence visual: Deltas provide fertile land for agriculture and act as natural buffers against storms.",
      "stock_footage_query": "",
      "user_footage_slot": {
        "reserved": false,
        "status": "empty",
        "notes": ""
      },
      "avatar_footage_slot": {
        "reserved": false,
        "status": "empty",
        "notes": ""
      },
      "reaction_footage_slot": {
        "reserved": false,
        "status": "empty",
        "notes": ""
      },
      "camera_movement": {
        "motion": "static",
        "angle": "",
        "shot_type": "medium"
      },
      "effect": {
        "name": "static",
        "zoom": {
          "start_scale": 1.0,
          "end_scale": 1.0
        },
        "pan": {
          "direction": "none",
          "amount_pct": 0.0
        },
        "ken_burns": false,
        "intensity": 45
      },
      "text_overlays": [
        {
          "text": "Deltas provide fertile land",
          "treatment": "",
          "start_sec": 18.0,
          "end_sec": 26.0
        }
      ],
      "caption_placement": "bottom third, safe zone",
      "sound_cues": [
        {
          "cue": "whoosh",
          "at_sec": 18.0,
          "track": "sfx"
        }
      ],
      "narration": "Deltas provide fertile land for agriculture and act as natural buffers against storms.",
      "duration_sec": 8.0,
      "resolved_asset": {
        "path": "runtime://image/demo",
        "uri": "",
        "image_url": "",
        "b64_json": "",
        "provider": "demo",
        "placeholder": true,
        "status": "mock",
        "prompt": "Evidence visual: Deltas provide fertile land for agriculture and act as natural buffers against storms.",
        "width": 1080,
        "height": 1920,
        "error": "",
        "scene_number": 4
      }
    },
    {
      "scene_id": 5,
      "visual_asset_type": "ai_image",
      "image_prompt": "Pattern Interrupt visual: Yet, climate change threatens these delicate areas. Why should we care?",
      "video_prompt": "Cinematic motion: Pattern Interrupt visual: Yet, climate change threatens these delicate areas. Why should we care?",
      "stock_footage_query": "",
      "user_footage_slot": {
        "reserved": false,
        "status": "empty",
        "notes": ""
      },
      "avatar_footage_slot": {
        "reserved": false,
        "status": "empty",
        "notes": ""
      },
      "reaction_footage_slot": {
        "reserved": false,
        "status": "empty",
        "notes": ""
      },
      "camera_movement": {
        "motion": "static",
        "angle": "",
        "shot_type": "medium"
      },
      "effect": {
        "name": "static",
        "zoom": {
          "start_scale": 1.0,
          "end_scale": 1.0
        },
        "pan": {
          "direction": "none",
          "amount_pct": 0.0
        },
        "ken_burns": false,
        "intensity": 45
      },
      "text_overlays": [
        {
          "text": "Yet, climate change threatens",
          "treatment": "",
          "start_sec": 26.0,
          "end_sec": 34.0
        }
      ],
      "caption_placement": "bottom third, safe zone",
      "sound_cues": [
        {
          "cue": "whoosh",
          "at_sec": 26.0,
          "track": "sfx"
        }
      ],
      "narration": "Yet, climate change threatens these delicate areas. Why should we care?",
      "duration_sec": 8.0,
      "resolved_asset": {}
    },
    {
      "scene_id": 6,
      "visual_asset_type": "ai_image",
      "image_prompt": "Payoff visual: By protecting deltas, we sustain biodiversity, secure food sources, and mitigate flooding.",
      "video_prompt": "Cinematic motion: Payoff visual: By protecting deltas, we sustain biodiversity, secure food sources, and mitigate flooding.",
      "stock_footage_query": "",
      "user_footage_slot": {
        "reserved": false,
        "status": "empty",
        "notes": ""
      },
      "avatar_footage_slot": {
        "reserved": false,
        "status": "empty",
        "notes": ""
      },
      "reaction_footage_slot": {
        "reserved": false,
        "status": "empty",
        "notes": ""
      },
      "camera_movement": {
        "motion": "static",
        "angle": "",
        "shot_type": "medium"
      },
      "effect": {
        "name": "static",
        "zoom": {
          "start_scale": 1.0,
          "end_scale": 1.0
        },
        "pan": {
          "direction": "none",
          "amount_pct": 0.0
        },
        "ken_burns": false,
        "intensity": 45
      },
      "text_overlays": [
        {
          "text": "By protecting deltas, we",
          "treatment": "",
          "start_sec": 34.0,
          "end_sec": 50.0
        }
      ],
      "caption_placement": "bottom third, safe zone",
      "sound_cues": [
        {
          "cue": "whoosh",
          "at_sec": 34.0,
          "track": "sfx"
        }
      ],
      "narration": "By protecting deltas, we sustain biodiversity, secure food sources, and mitigate flooding.",
      "duration_sec": 16.0,
      "resolved_asset": {}
    },
    {
      "scene_id": 7,
      "visual_asset_type": "ai_image",
      "image_prompt": "Cta visual: Follow for more fascinating science insights!",
      "video_prompt": "Cinematic motion: Cta visual: Follow for more fascinating science insights!",
      "stock_footage_query": "",
      "user_footage_slot": {
        "reserved": false,
        "status": "empty",
        "notes": ""
      },
      "avatar_footage_slot": {
        "reserved": false,
        "status": "empty",
        "notes": ""
      },
      "reaction_footage_slot": {
        "reserved": false,
        "status": "empty",
        "notes": ""
      },
      "camera_movement": {
        "motion": "static",
        "angle": "",
        "shot_type": "medium"
      },
      "effect": {
        "name": "static",
        "zoom": {
          "start_scale": 1.0,
          "end_scale": 1.0
        },
        "pan": {
          "direction": "none",
          "amount_pct": 0.0
        },
        "ken_burns": false,
        "intensity": 45
      },
      "text_overlays": [
        {
          "text": "Follow for more fascinating",
          "treatment": "",
          "start_sec": 50.0,
          "end_sec": 60.0
        }
      ],
      "caption_placement": "bottom third, safe zone",
      "sound_cues": [
        {
          "cue": "whoosh",
          "at_sec": 50.0,
          "track": "sfx"
        }
      ],
      "narration": "Follow for more fascinating science insights!",
      "duration_sec": 10.0,
      "resolved_asset": {}
    }
  ],
  "caption_render_plan": {
    "mode": "word_by_word",
    "style_preset": "bold_pop",
    "style": {
      "font": "Montserrat ExtraBold",
      "size_pct": 4.8,
      "fill": "#FFFFFF",
      "stroke": "#000000",
      "stroke_width_px": 6,
      "emphasis_fill": "#FFD400",
      "animation": "word pop 1.08x on entry",
      "case": "upper"
    },
    "available_presets": [
      "bold_pop",
      "clean_minimal",
      "karaoke_highlight",
      "documentary_lower_third"
    ],
    "safe_area": {
      "top_pct": 12.0,
      "bottom_pct": 20.0,
      "left_pct": 6.0,
      "right_pct": 12.0
    },
    "platform_layouts": {
      "youtube_shorts": {
        "anchor_y_pct": 68.0,
        "notes": "clear the title/channel block at the bottom"
      },
      "tiktok": {
        "anchor_y_pct": 64.0,
        "notes": "clear caption + music marquee, keep off the right rail"
      },
      "instagram_reels": {
        "anchor_y_pct": 66.0,
        "notes": "clear the audio attribution row"
      },
      "facebook_reels": {
        "anchor_y_pct": 66.0,
        "notes": "mirror the Reels layout"
      }
    },
    "segments": [
      {
        "scene_id": 1,
        "mode": "word_by_word",
        "start_sec": 0.0,
        "end_sec": 2.0,
        "sentence": "Science has a clearer story about river deltas than social media does.",
        "words": [
          {
            "word": "Science",
            "start_sec": 0.0,
            "end_sec": 0.22,
            "emphasis": true
          },
          {
            "word": "has",
            "start_sec": 0.22,
            "end_sec": 0.34,
            "emphasis": false
          },
          {
            "word": "a",
            "start_sec": 0.34,
            "end_sec": 0.41,
            "emphasis": false
          },
          {
            "word": "clearer",
            "start_sec": 0.41,
            "end_sec": 0.63,
            "emphasis": true
          },
          {
            "word": "story",
            "start_sec": 0.63,
            "end_sec": 0.8,
            "emphasis": false
          },
          {
            "word": "about",
            "start_sec": 0.8,
            "end_sec": 0.98,
            "emphasis": false
          },
          {
            "word": "river",
            "start_sec": 0.98,
            "end_sec": 1.15,
            "emphasis": false
          },
          {
            "word": "deltas",
            "start_sec": 1.15,
            "end_sec": 1.34,
            "emphasis": false
          },
          {
            "word": "than",
            "start_sec": 1.34,
            "end_sec": 1.49,
            "emphasis": false
          },
          {
            "word": "social",
            "start_sec": 1.49,
            "end_sec": 1.68,
            "emphasis": false
          },
          {
            "word": "media",
            "start_sec": 1.68,
            "end_sec": 1.85,
            "emphasis": false
          },
          {
            "word": "does",
            "start_sec": 1.85,
            "end_sec": 2.0,
            "emphasis": false
          }
        ],
        "emphasis_words": [
          "Science",
          "clearer"
        ],
        "placement": "bottom third, safe zone"
      },
      {
        "scene_id": 2,
        "mode": "word_by_word",
        "start_sec": 2.0,
        "end_sec": 10.0,
        "sentence": "River deltas form where rivers meet the sea, creating unique ecosystems.",
        "words": [
          {
            "word": "River",
            "start_sec": 2.0,
            "end_sec": 2.68,
            "emphasis": false
          },
          {
            "word": "deltas",
            "start_sec": 2.68,
            "end_sec": 3.46,
            "emphasis": false
          },
          {
            "word": "form",
            "start_sec": 3.46,
            "end_sec": 4.05,
            "emphasis": false
          },
          {
            "word": "where",
            "start_sec": 4.05,
            "end_sec": 4.73,
            "emphasis": false
          },
          {
            "word": "rivers",
            "start_sec": 4.73,
            "end_sec": 5.51,
            "emphasis": false
          },
          {
            "word": "meet",
            "start_sec": 5.51,
            "end_sec": 6.1,
            "emphasis": false
          },
          {
            "word": "the",
            "start_sec": 6.1,
            "end_sec": 6.59,
            "emphasis": false
          },
          {
            "word": "sea",
            "start_sec": 6.59,
            "end_sec": 7.07,
            "emphasis": false
          },
          {
            "word": "creating",
            "start_sec": 7.07,
            "end_sec": 8.05,
            "emphasis": false
          },
          {
            "word": "unique",
            "start_sec": 8.05,
            "end_sec": 8.83,
            "emphasis": false
          },
          {
            "word": "ecosystems",
            "start_sec": 8.83,
            "end_sec": 10.0,
            "emphasis": true
          }
        ],
        "emphasis_words": [
          "ecosystems"
        ],
        "placement": "bottom third, safe zone"
      },
      {
        "scene_id": 3,
        "mode": "word_by_word",
        "start_sec": 10.0,
        "end_sec": 18.0,
        "sentence": "But did you know they're also vital for human life?",
        "words": [
          {
            "word": "But",
            "start_sec": 10.0,
            "end_sec": 10.66,
            "emphasis": false
          },
          {
            "word": "did",
            "start_sec": 10.66,
            "end_sec": 11.31,
            "emphasis": false
          },
          {
            "word": "you",
            "start_sec": 11.31,
            "end_sec": 11.97,
            "emphasis": false
          },
          {
            "word": "know",
            "start_sec": 11.97,
            "end_sec": 12.75,
            "emphasis": false
          },
          {
            "word": "they're",
            "start_sec": 12.75,
            "end_sec": 13.93,
            "emphasis": true
          },
          {
            "word": "also",
            "start_sec": 13.93,
            "end_sec": 14.72,
            "emphasis": false
          },
          {
            "word": "vital",
            "start_sec": 14.72,
            "end_sec": 15.64,
            "emphasis": false
          },
          {
            "word": "for",
            "start_sec": 15.64,
            "end_sec": 16.3,
            "emphasis": false
          },
          {
            "word": "human",
            "start_sec": 16.3,
            "end_sec": 17.21,
            "emphasis": false
          },
          {
            "word": "life",
            "start_sec": 17.21,
            "end_sec": 18.0,
            "emphasis": false
          }
        ],
        "emphasis_words": [
          "they're"
        ],
        "placement": "bottom third, safe zone"
      },
      {
        "scene_id": 4,
        "mode": "word_by_word",
        "start_sec": 18.0,
        "end_sec": 26.0,
        "sentence": "Deltas provide fertile land for agriculture and act as natural buffers against storms.",
        "words": [
          {
            "word": "Deltas",
            "start_sec": 18.0,
            "end_sec": 18.65,
            "emphasis": false
          },
          {
            "word": "provide",
            "start_sec": 18.65,
            "end_sec": 19.37,
            "emphasis": true
          },
          {
            "word": "fertile",
            "start_sec": 19.37,
            "end_sec": 20.1,
            "emphasis": false
          },
          {
            "word": "land",
            "start_sec": 20.1,
            "end_sec": 20.59,
            "emphasis": false
          },
          {
            "word": "for",
            "start_sec": 20.59,
            "end_sec": 20.99,
            "emphasis": false
          },
          {
            "word": "agriculture",
            "start_sec": 20.99,
            "end_sec": 22.04,
            "emphasis": true
          },
          {
            "word": "and",
            "start_sec": 22.04,
            "end_sec": 22.44,
            "emphasis": false
          },
          {
            "word": "act",
            "start_sec": 22.44,
            "end_sec": 22.85,
            "emphasis": false
          },
          {
            "word": "as",
            "start_sec": 22.85,
            "end_sec": 23.17,
            "emphasis": false
          },
          {
            "word": "natural",
            "start_sec": 23.17,
            "end_sec": 23.9,
            "emphasis": false
          },
          {
            "word": "buffers",
            "start_sec": 23.9,
            "end_sec": 24.63,
            "emphasis": false
          },
          {
            "word": "against",
            "start_sec": 24.63,
            "end_sec": 25.35,
            "emphasis": false
          },
          {
            "word": "storms",
            "start_sec": 25.35,
            "end_sec": 26.0,
            "emphasis": false
          }
        ],
        "emphasis_words": [
          "agriculture",
          "provide"
        ],
        "placement": "bottom third, safe zone"
      },
      {
        "scene_id": 5,
        "mode": "word_by_word",
        "start_sec": 26.0,
        "end_sec": 34.0,
        "sentence": "Yet, climate change threatens these delicate areas. Why should we care?",
        "words": [
          {
            "word": "Yet",
            "start_sec": 26.0,
            "end_sec": 26.5,
            "emphasis": false
          },
          {
            "word": "climate",
            "start_sec": 26.5,
            "end_sec": 27.4,
            "emphasis": false
          },
          {
            "word": "change",
            "start_sec": 27.4,
            "end_sec": 28.2,
            "emphasis": false
          },
          {
            "word": "threatens",
            "start_sec": 28.2,
            "end_sec": 29.3,
            "emphasis": true
          },
          {
            "word": "these",
            "start_sec": 29.3,
            "end_sec": 30.0,
            "emphasis": false
          },
          {
            "word": "delicate",
            "start_sec": 30.0,
            "end_sec": 31.0,
            "emphasis": false
          },
          {
            "word": "areas",
            "start_sec": 31.0,
            "end_sec": 31.7,
            "emphasis": false
          },
          {
            "word": "Why",
            "start_sec": 31.7,
            "end_sec": 32.2,
            "emphasis": false
          },
          {
            "word": "should",
            "start_sec": 32.2,
            "end_sec": 33.0,
            "emphasis": false
          },
          {
            "word": "we",
            "start_sec": 33.0,
            "end_sec": 33.4,
            "emphasis": false
          },
          {
            "word": "care",
            "start_sec": 33.4,
            "end_sec": 34.0,
            "emphasis": false
          }
        ],
        "emphasis_words": [
          "threatens"
        ],
        "placement": "bottom third, safe zone"
      },
      {
        "scene_id": 6,
        "mode": "word_by_word",
        "start_sec": 34.0,
        "end_sec": 50.0,
        "sentence": "By protecting deltas, we sustain biodiversity, secure food sources, and mitigate flooding.",
        "words": [
          {
            "word": "By",
            "start_sec": 34.0,
            "end_sec": 34.65,
            "emphasis": false
          },
          {
            "word": "protecting",
            "start_sec": 34.65,
            "end_sec": 36.59,
            "emphasis": true
          },
          {
            "word": "deltas",
            "start_sec": 36.59,
            "end_sec": 37.88,
            "emphasis": false
          },
          {
            "word": "we",
            "start_sec": 37.88,
            "end_sec": 38.53,
            "emphasis": false
          },
          {
            "word": "sustain",
            "start_sec": 38.53,
            "end_sec": 39.98,
            "emphasis": false
          },
          {
            "word": "biodiversity",
            "start_sec": 39.98,
            "end_sec": 42.24,
            "emphasis": true
          },
          {
            "word": "secure",
            "start_sec": 42.24,
            "end_sec": 43.54,
            "emphasis": false
          },
          {
            "word": "food",
            "start_sec": 43.54,
            "end_sec": 44.51,
            "emphasis": false
          },
          {
            "word": "sources",
            "start_sec": 44.51,
            "end_sec": 45.96,
            "emphasis": false
          },
          {
            "word": "and",
            "start_sec": 45.96,
            "end_sec": 46.77,
            "emphasis": false
          },
          {
            "word": "mitigate",
            "start_sec": 46.77,
            "end_sec": 48.38,
            "emphasis": false
          },
          {
            "word": "flooding",
            "start_sec": 48.38,
            "end_sec": 50.0,
            "emphasis": false
          }
        ],
        "emphasis_words": [
          "biodiversity",
          "protecting"
        ],
        "placement": "bottom third, safe zone"
      },
      {
        "scene_id": 7,
        "mode": "word_by_word",
        "start_sec": 50.0,
        "end_sec": 60.0,
        "sentence": "Follow for more fascinating science insights!",
        "words": [
          {
            "word": "Follow",
            "start_sec": 50.0,
            "end_sec": 51.57,
            "emphasis": false
          },
          {
            "word": "for",
            "start_sec": 51.57,
            "end_sec": 52.55,
            "emphasis": false
          },
          {
            "word": "more",
            "start_sec": 52.55,
            "end_sec": 53.73,
            "emphasis": false
          },
          {
            "word": "fascinating",
            "start_sec": 53.73,
            "end_sec": 56.27,
            "emphasis": true
          },
          {
            "word": "science",
            "start_sec": 56.27,
            "end_sec": 58.04,
            "emphasis": false
          },
          {
            "word": "insights",
            "start_sec": 58.04,
            "end_sec": 60.0,
            "emphasis": false
          }
        ],
        "emphasis_words": [
          "fascinating"
        ],
        "placement": "bottom third, safe zone"
      }
    ]
  },
  "audio_mix_plan": {
    "duration_sec": 60.0,
    "tracks": {
      "narration": {
        "level_db": -3.0,
        "voice_style": {},
        "segments": [
          {
            "scene_id": 1,
            "start_sec": 0.0,
            "end_sec": 2.0,
            "text": "Science has a clearer story about river deltas than social media does.",
            "delivery": "",
            "target_wpm": 0,
            "pauses": [],
            "emphasis": [],
            "path": "data/productions/sp100w5_earth_064_river_deltas_001/voice.mp3"
          },
          {
            "scene_id": 2,
            "start_sec": 2.0,
            "end_sec": 10.0,
            "text": "River deltas form where rivers meet the sea, creating unique ecosystems.",
            "delivery": "",
            "target_wpm": 0,
            "pauses": [],
            "emphasis": [],
            "path": "data/productions/sp100w5_earth_064_river_deltas_001/voice.mp3"
          },
          {
            "scene_id": 3,
            "start_sec": 10.0,
            "end_sec": 18.0,
            "text": "But did you know they're also vital for human life?",
            "delivery": "",
            "target_wpm": 0,
            "pauses": [],
            "emphasis": [],
            "path": "data/productions/sp100w5_earth_064_river_deltas_001/voice.mp3"
          },
          {
            "scene_id": 4,
            "start_sec": 18.0,
            "end_sec": 26.0,
            "text": "Deltas provide fertile land for agriculture and act as natural buffers against storms.",
            "delivery": "",
            "target_wpm": 0,
            "pauses": [],
            "emphasis": [],
            "path": "data/productions/sp100w5_earth_064_river_deltas_001/voice.mp3"
          },
          {
            "scene_id": 5,
            "start_sec": 26.0,
            "end_sec": 34.0,
            "text": "Yet, climate change threatens these delicate areas. Why should we care?",
            "delivery": "",
            "target_wpm": 0,
            "pauses": [],
            "emphasis": [],
            "path": "data/productions/sp100w5_earth_064_river_deltas_001/voice.mp3"
          },
          {
            "scene_id": 6,
            "start_sec": 34.0,
            "end_sec": 50.0,
            "text": "By protecting deltas, we sustain biodiversity, secure food sources, and mitigate flooding.",
            "delivery": "",
            "target_wpm": 0,
            "pauses": [],
            "emphasis": [],
            "path": "data/productions/sp100w5_earth_064_river_deltas_001/voice.mp3"
          },
          {
            "scene_id": 7,
            "start_sec": 50.0,
            "end_sec": 60.0,
            "text": "Follow for more fascinating science insights!",
            "delivery": "",
            "target_wpm": 0,
            "pauses": [],
            "emphasis": [],
            "path": "data/productions/sp100w5_earth_064_river_deltas_001/voice.mp3"
          }
        ]
      },
      "music": {
        "level_db": -18.0,
        "style": "educational ambient",
        "bpm_range": [
          90,
          120
        ],
        "energy_curve": [
          "rise",
          "sustain",
          "resolve"
        ],
        "ducking": {
          "enabled": true,
          "trigger": "narration",
          "duck_to_db": -26.0,
          "attack_ms": 150,
          "release_ms": 400
        }
      },
      "sfx": {
        "level_db": -10.0,
        "cues": [
          {
            "scene_id": 1,
            "cue": "bass hit",
            "at_sec": 0.0
          },
          {
            "scene_id": 2,
            "cue": "whoosh",
            "at_sec": 2.0
          },
          {
            "scene_id": 3,
            "cue": "whoosh",
            "at_sec": 10.0
          },
          {
            "scene_id": 4,
            "cue": "whoosh",
            "at_sec": 18.0
          },
          {
            "scene_id": 5,
            "cue": "whoosh",
            "at_sec": 26.0
          },
          {
            "scene_id": 6,
            "cue": "whoosh",
            "at_sec": 34.0
          },
          {
            "scene_id": 7,
            "cue": "whoosh",
            "at_sec": 50.0
          }
        ]
      },
      "transitions": {
        "level_db": -12.0,
        "cues": []
      }
    },
    "silence_drops": [
      {
        "scene_id": 5,
        "at_sec": 25.6,
        "duration_sec": 0.4,
        "reason": "drop the full mix before the pattern_interrupt beat"
      },
      {
        "scene_id": 6,
        "at_sec": 33.6,
        "duration_sec": 0.4,
        "reason": "drop the full mix before the payoff beat"
      }
    ],
    "loudness_target": {
      "standard": "platform_safe_placeholder",
      "integrated_lufs": -14.0,
      "true_peak_db": -1.0,
      "notes": "Verify with a real loudness pass when actual audio is rendered."
    }
  },
  "transition_plan": {
    "supported_types": [
      "cut",
      "fade",
      "push",
      "zoom",
      "whip_pan",
      "glitch",
      "flash",
      "documentary_slow_zoom",
      "cinematic_push_in",
      "quick_cut"
    ],
    "transitions": [
      {
        "from_scene": 1,
        "to_scene": 2,
        "type": "cut",
        "duration_sec": 0.0,
        "sound_cue": "",
        "source_language": "hard cut"
      },
      {
        "from_scene": 2,
        "to_scene": 3,
        "type": "cut",
        "duration_sec": 0.0,
        "sound_cue": "",
        "source_language": "hard cut"
      },
      {
        "from_scene": 3,
        "to_scene": 4,
        "type": "cut",
        "duration_sec": 0.0,
        "sound_cue": "",
        "source_language": "hard cut"
      },
      {
        "from_scene": 4,
        "to_scene": 5,
        "type": "cut",
        "duration_sec": 0.0,
        "sound_cue": "",
        "source_language": "hard cut"
      },
      {
        "from_scene": 5,
        "to_scene": 6,
        "type": "cut",
        "duration_sec": 0.0,
        "sound_cue": "",
        "source_language": "hard cut"
      },
      {
        "from_scene": 6,
        "to_scene": 7,
        "type": "cut",
        "duration_sec": 0.0,
        "sound_cue": "",
        "source_language": "hard cut"
      }
    ],
    "warnings": []
  },
  "motion_plan": [
    {
      "scene_id": 1,
      "effect": "quick_punch_in",
      "intensity": 70,
      "duration_sec": 2.0,
      "zoom": {
        "start_scale": 1.0,
        "end_scale": 1.188
      },
      "pan": {
        "direction": "none",
        "amount_pct": 0.0
      },
      "ken_burns": false,
      "easing": "ease_out"
    },
    {
      "scene_id": 2,
      "effect": "static",
      "intensity": 45,
      "duration_sec": 8.0,
      "zoom": {
        "start_scale": 1.0,
        "end_scale": 1.0
      },
      "pan": {
        "direction": "none",
        "amount_pct": 0.0
      },
      "ken_burns": false,
      "easing": "ease_in_out"
    },
    {
      "scene_id": 3,
      "effect": "static",
      "intensity": 45,
      "duration_sec": 8.0,
      "zoom": {
        "start_scale": 1.0,
        "end_scale": 1.0
      },
      "pan": {
        "direction": "none",
        "amount_pct": 0.0
      },
      "ken_burns": false,
      "easing": "ease_in_out"
    },
    {
      "scene_id": 4,
      "effect": "static",
      "intensity": 45,
      "duration_sec": 8.0,
      "zoom": {
        "start_scale": 1.0,
        "end_scale": 1.0
      },
      "pan": {
        "direction": "none",
        "amount_pct": 0.0
      },
      "ken_burns": false,
      "easing": "ease_in_out"
    },
    {
      "scene_id": 5,
      "effect": "static",
      "intensity": 45,
      "duration_sec": 8.0,
      "zoom": {
        "start_scale": 1.0,
        "end_scale": 1.0
      },
      "pan": {
        "direction": "none",
        "amount_pct": 0.0
      },
      "ken_burns": false,
      "easing": "ease_in_out"
    },
    {
      "scene_id": 6,
      "effect": "static",
      "intensity": 45,
      "duration_sec": 16.0,
      "zoom": {
        "start_scale": 1.0,
        "end_scale": 1.0
      },
      "pan": {
        "direction": "none",
        "amount_pct": 0.0
      },
      "ken_burns": false,
      "easing": "ease_in_out"
    },
    {
      "scene_id": 7,
      "effect": "static",
      "intensity": 45,
      "duration_sec": 10.0,
      "zoom": {
        "start_scale": 1.0,
        "end_scale": 1.0
      },
      "pan": {
        "direction": "none",
        "amount_pct": 0.0
      },
      "ken_burns": false,
      "easing": "ease_in_out"
    }
  ],
  "asset_requirements": [],
  "missing_assets": [],
  "render_warnings": [],
  "estimated_render_duration_sec": 60.0,
  "production_readiness_score": 100,
  "validation": {
    "status": "SUCCESS",
    "checks": [
      {
        "check": "scenes_present",
        "passed": true,
        "detail": "7 scenes in the plan."
      },
      {
        "check": "scenes_have_visuals",
        "passed": true,
        "detail": "Every scene has a visual asset or prompt."
      },
      {
        "check": "scenes_have_narration",
        "passed": true,
        "detail": "Every scene has narration."
      },
      {
        "check": "captions_exist",
        "passed": true,
        "detail": "7 caption segments planned."
      },
      {
        "check": "audio_plan_exists",
        "passed": true,
        "detail": "Audio mix plan covers narration/music/SFX tracks."
      },
      {
        "check": "runtime_reasonable",
        "passed": true,
        "detail": "Total runtime 60.0s is inside the 5.0-180.0s short-form window."
      },
      {
        "check": "output_format_supported",
        "passed": true,
        "detail": "9:16 1080x1920 MP4 \u2014 supported."
      },
      {
        "check": "assets_resolved",
        "passed": true,
        "detail": "All asset requests were fulfilled."
      }
    ],
    "problems": [],
    "production_readiness_score": 100
  },
  "render_status": "SUCCESS",
  "mock_output_path": "data/productions/sp100w5_earth_064_river_deltas_001/render.mp4",
  "output_path": "data/productions/sp100w5_earth_064_river_deltas_001/render.mp4",
  "mp4_path": "data/productions/sp100w5_earth_064_river_deltas_001/render.mp4",
  "file_uri": "data/productions/sp100w5_earth_064_river_deltas_001/render.mp4",
  "render_log": [
    "color_bed\u2192mp4 (no visual assets resolved)",
    "ffmpeg_exit=0"
  ],
  "render_job": {},
  "mock": false,
  "assembly": {
    "ok": true,
    "mock": false,
    "error": "",
    "output_path": "data/productions/sp100w5_earth_064_river_deltas_001/render.mp4",
    "absolute_path": "/Users/jaredbrottem/Desktop/AI Start-UP/Apps/generational/data/productions/sp100w5_earth_064_river_deltas_001/render.mp4",
    "bytes": 384303,
    "duration_sec": 60.0,
    "resolution": "1080x1920",
    "ffmpeg": "/Users/jaredbrottem/Desktop/AI Start-UP/Apps/generational/venv/lib/python3.9/site-packages/imageio_ffmpeg/binaries/ffmpeg-macos-aarch64-v7.1",
    "log": [
      "color_bed\u2192mp4 (no visual assets resolved)",
      "ffmpeg_exit=0"
    ],
    "visual_count": 0,
    "has_audio": true,
    "manifest": {
      "title": "River deltas",
      "format": {
        "aspect_ratio": "9:16",
        "resolution": {
          "width": 1080,
          "height": 1920
        },
        "container": "mp4",
        "video_codec": "h264",
        "audio_codec": "aac",
        "fps": 30,
        "orientation": "vertical",
        "platforms": [
          "youtube_shorts",
          "tiktok",
          "instagram_reels",
          "facebook_reels"
        ]
      },
      "visuals": [],
      "audio": "/Users/jaredbrottem/Desktop/AI Start-UP/Apps/generational/data/productions/sp100w5_earth_064_river_deltas_001/voice.mp3"
    }
  },
  "render_manifest": {
    "scenes": 7,
    "timeline_segments": 7,
    "caption_segments": 7,
    "audio_tracks": [
      "narration",
      "music",
      "sfx",
      "transitions"
    ],
    "transitions": 6,
    "assets_requested": 0,
    "assets_missing": 0,
    "warnings": 0,
    "readiness": 100,
    "ready_for_publishing": true,
    "real_mp4": true
  }
}