{
  "title": "System 1 System 2",
  "description": "Explain System 1 System 2 accurately for a general audience. Use established science; mark uncertainty. No sensationalism.",
  "hashtags": [
    "#mind",
    "#science",
    "#education",
    "#shorts"
  ],
  "mp4_path": "data/productions/sp100w5_mind_112_system_1_system_2_001/render.mp4",
  "thumbnail": "",
  "platform": "youtube_shorts",
  "ready": false,
  "status": "awaiting_oauth",
  "note": "Publishing credentials unavailable \u2014 stopped after MP4 export"
}