{
  "title": "Autophagy basics",
  "description": "Explain autophagy basics accurately for a general audience. Use established science; mark uncertainty. No sensationalism.",
  "hashtags": [
    "#bio",
    "#science",
    "#education",
    "#shorts"
  ],
  "cta": "Like and follow for more insights.",
  "duration_sec": 60.0,
  "mp4_path": "data/productions/sp100w5_bio_040_autophagy_basics_001/render.mp4",
  "final_export_path": "/Users/jaredbrottem/Desktop/AI Start-up/videos/test run generational/2026-07-10_12-39-21_Autophagy_basics.mp4",
  "final_export_dir": "/Users/jaredbrottem/Desktop/AI Start-up/videos/test run generational",
  "platform": "youtube_shorts",
  "generated_at": "2026-07-10T17:39:21.263597+00:00",
  "ready_to_post": true
}