{
  "title": "The Gut-Brain Axis Explained",
  "description": "Explain the gut-brain axis: vagus nerve, microbial metabolites, mood research. Mark microbiome-mood claims as emerging where evidence is preliminary. Ground in NIH/peer-reviewed gastroenterology and neuroscience reviews.",
  "hashtags": [
    "#microbiome",
    "#neuroscience",
    "#health",
    "#shorts"
  ],
  "mp4_path": "data/productions/sp100_gut_brain_001/render.mp4",
  "thumbnail": "",
  "platform": "youtube_shorts",
  "ready": false,
  "status": "awaiting_oauth",
  "note": "Publishing credentials unavailable \u2014 stopped after MP4 export"
}