[
  {
    "scene_number": 1,
    "purpose": "hook",
    "emotion": "curiosity",
    "length_sec": 2.0,
    "narration": "Here's what science actually says about prebiotics.",
    "visual_description": "Hook visual: Here's what science actually says about prebiotics.",
    "camera_motion": "subtle push",
    "zoom": "punch-in",
    "motion_intensity": 70,
    "transition_in": "none",
    "transition_out": "hard cut",
    "asset_type": "ai_image",
    "ai_image_prompt": "Hook visual: Here's what science actually says about prebiotics.",
    "ai_video_prompt": "Cinematic motion: Hook visual: Here's what science actually says about prebiotics.",
    "stock_footage_query": "",
    "text_overlay": "Here's what science actually",
    "overlay": "",
    "caption_placement": "bottom third, safe zone",
    "caption_timing": {
      "start_sec": 0.0,
      "end_sec": 2.0
    },
    "caption_emphasis": [],
    "sound_effect": "bass hit",
    "sfx_timing": {
      "cue": "bass hit",
      "at_sec": 0.0
    }
  },
  {
    "scene_number": 2,
    "purpose": "context",
    "emotion": "curiosity",
    "length_sec": 8.0,
    "narration": "Prebiotics are types of fiber that feed your good gut bacteria.",
    "visual_description": "Context visual: Prebiotics are types of fiber that feed your good gut bacteria.",
    "camera_motion": "static",
    "zoom": "",
    "motion_intensity": 45,
    "transition_in": "cut",
    "transition_out": "hard cut",
    "asset_type": "ai_image",
    "ai_image_prompt": "Context visual: Prebiotics are types of fiber that feed your good gut bacteria.",
    "ai_video_prompt": "Cinematic motion: Context visual: Prebiotics are types of fiber that feed your good gut bacteria.",
    "stock_footage_query": "",
    "text_overlay": "Prebiotics are types of",
    "overlay": "",
    "caption_placement": "bottom third, safe zone",
    "caption_timing": {
      "start_sec": 2.0,
      "end_sec": 10.0
    },
    "caption_emphasis": [],
    "sound_effect": "whoosh",
    "sfx_timing": {
      "cue": "whoosh",
      "at_sec": 2.0
    }
  },
  {
    "scene_number": 3,
    "purpose": "escalation",
    "emotion": "concern",
    "length_sec": 8.0,
    "narration": "Without them, your microbiome can struggle, leading to digestive issues.",
    "visual_description": "Escalation visual: Without them, your microbiome can struggle, leading to digestive issues.",
    "camera_motion": "static",
    "zoom": "",
    "motion_intensity": 45,
    "transition_in": "cut",
    "transition_out": "hard cut",
    "asset_type": "ai_image",
    "ai_image_prompt": "Escalation visual: Without them, your microbiome can struggle, leading to digestive issues.",
    "ai_video_prompt": "Cinematic motion: Escalation visual: Without them, your microbiome can struggle, leading to digestive issues.",
    "stock_footage_query": "",
    "text_overlay": "Without them, your microbiome",
    "overlay": "",
    "caption_placement": "bottom third, safe zone",
    "caption_timing": {
      "start_sec": 10.0,
      "end_sec": 18.0
    },
    "caption_emphasis": [],
    "sound_effect": "whoosh",
    "sfx_timing": {
      "cue": "whoosh",
      "at_sec": 10.0
    }
  },
  {
    "scene_number": 4,
    "purpose": "evidence",
    "emotion": "hope",
    "length_sec": 8.0,
    "narration": "Studies show prebiotics can improve gut health and boost immunity.",
    "visual_description": "Evidence visual: Studies show prebiotics can improve gut health and boost immunity.",
    "camera_motion": "static",
    "zoom": "",
    "motion_intensity": 45,
    "transition_in": "cut",
    "transition_out": "hard cut",
    "asset_type": "ai_image",
    "ai_image_prompt": "Evidence visual: Studies show prebiotics can improve gut health and boost immunity.",
    "ai_video_prompt": "Cinematic motion: Evidence visual: Studies show prebiotics can improve gut health and boost immunity.",
    "stock_footage_query": "",
    "text_overlay": "Studies show prebiotics can",
    "overlay": "",
    "caption_placement": "bottom third, safe zone",
    "caption_timing": {
      "start_sec": 18.0,
      "end_sec": 26.0
    },
    "caption_emphasis": [],
    "sound_effect": "whoosh",
    "sfx_timing": {
      "cue": "whoosh",
      "at_sec": 18.0
    }
  },
  {
    "scene_number": 5,
    "purpose": "payoff",
    "emotion": "surprise",
    "length_sec": 8.0,
    "narration": "But here's the twist: not all prebiotics are created equal!",
    "visual_description": "Payoff visual: But here's the twist: not all prebiotics are created equal!",
    "camera_motion": "static",
    "zoom": "",
    "motion_intensity": 45,
    "transition_in": "cut",
    "transition_out": "hard cut",
    "asset_type": "ai_image",
    "ai_image_prompt": "Payoff visual: But here's the twist: not all prebiotics are created equal!",
    "ai_video_prompt": "Cinematic motion: Payoff visual: But here's the twist: not all prebiotics are created equal!",
    "stock_footage_query": "",
    "text_overlay": "But here's the twist:",
    "overlay": "",
    "caption_placement": "bottom third, safe zone",
    "caption_timing": {
      "start_sec": 26.0,
      "end_sec": 34.0
    },
    "caption_emphasis": [],
    "sound_effect": "whoosh",
    "sfx_timing": {
      "cue": "whoosh",
      "at_sec": 26.0
    }
  },
  {
    "scene_number": 6,
    "purpose": "pattern_interrupt",
    "emotion": "curiosity",
    "length_sec": 16.0,
    "narration": "Some early research suggests that the wrong types can actually cause bloating.",
    "visual_description": "Pattern Interrupt visual: Some early research suggests that the wrong types can actually cause bloating.",
    "camera_motion": "static",
    "zoom": "",
    "motion_intensity": 45,
    "transition_in": "cut",
    "transition_out": "hard cut",
    "asset_type": "ai_image",
    "ai_image_prompt": "Pattern Interrupt visual: Some early research suggests that the wrong types can actually cause bloating.",
    "ai_video_prompt": "Cinematic motion: Pattern Interrupt visual: Some early research suggests that the wrong types can actually cause bloating.",
    "stock_footage_query": "",
    "text_overlay": "Some early research suggests",
    "overlay": "",
    "caption_placement": "bottom third, safe zone",
    "caption_timing": {
      "start_sec": 34.0,
      "end_sec": 50.0
    },
    "caption_emphasis": [],
    "sound_effect": "whoosh",
    "sfx_timing": {
      "cue": "whoosh",
      "at_sec": 34.0
    }
  },
  {
    "scene_number": 7,
    "purpose": "cta",
    "emotion": "encouragement",
    "length_sec": 10.0,
    "narration": "Want to unlock the secrets of gut health? Follow for more insights!",
    "visual_description": "Cta visual: Want to unlock the secrets of gut health? Follow for more insights!",
    "camera_motion": "static",
    "zoom": "",
    "motion_intensity": 45,
    "transition_in": "cut",
    "transition_out": "hard cut",
    "asset_type": "ai_image",
    "ai_image_prompt": "Cta visual: Want to unlock the secrets of gut health? Follow for more insights!",
    "ai_video_prompt": "Cinematic motion: Cta visual: Want to unlock the secrets of gut health? Follow for more insights!",
    "stock_footage_query": "",
    "text_overlay": "Want to unlock the",
    "overlay": "",
    "caption_placement": "bottom third, safe zone",
    "caption_timing": {
      "start_sec": 50.0,
      "end_sec": 60.0
    },
    "caption_emphasis": [],
    "sound_effect": "whoosh",
    "sfx_timing": {
      "cue": "whoosh",
      "at_sec": 50.0
    }
  }
]